{
    "adatLista": [
      {
        "id": 1,
        "gyarto": "Ford",
        "nev": "Mustang GT Fastback",
        "evjarat": 1967
      },
      {
        "id": 2,
        "gyarto": "Jaguar",
        "nev": "E-type",
        "evjarat": 1967
      },
      {
        "id": 3,
        "gyarto": "Lamborghini",
        "nev": "Murcielago",
        "evjarat": 2001
      },
      {
        "id": 4,
        "gyarto": "Lancia",
        "nev": "Stratos",
        "evjarat": 1972
      },
      {
        "id": 5,
        "gyarto": "Lexus",
        "nev": "LFA",
        "evjarat": 2010
      },
      {
        "id": 6,
        "gyarto": "Mazda",
        "nev": "NA Miata",
        "evjarat": 1996
      },
      {
        "id": 7,
        "gyarto": "McLaren",
        "nev": "F1",
        "evjarat": 1992
      },
      {
        "id": 8,
        "gyarto": "Toyota",
        "nev": "Supra",
        "evjarat": 1994
      }
    ]
  }